custom_git-4.6.data/scripts/delete_project.sh
custom_git-4.6.data/scripts/excute.sh
custom_git-4.6.data/scripts/execute.sh
jupyterlab_git/__init__.py
jupyterlab_git/git.py
jupyterlab_git/handlers.py
tests/__init__.py
tests/test_branch.py
tests/test_clone.py
tests/test_config.py
tests/test_diff.py
tests/test_handlers.py
tests/test_pushpull.py
tests/unit/__init__.py
tests/unit/test_branch.py
tests/unit/test_clone.py
tests/unit/test_config.py
tests/unit/test_diff.py
tests/unit/test_handlers.py
tests/unit/test_pushpull.py
custom_git-4.6.dist-info/LICENSE
custom_git-4.6.dist-info/METADATA
custom_git-4.6.dist-info/WHEEL
custom_git-4.6.dist-info/top_level.txt
custom_git-4.6.dist-info/RECORD
