Metadata-Version: 2.1
Name: custom-git
Version: 4.6
Summary: A Docker and AWS utility package
Home-page: https://github.com/voziq/custom-git
Author: voziq
Author-email: mgoli@voziq.com
License: UNKNOWN
Platform: UNKNOWN
Requires-Dist: notebook
Requires-Dist: nbdime (>=1.1.0)
